odoo9_addon_contract_digitized_signature-9.0.1.0.0-py2.7-nspkg.pth
odoo9_addon_contract_digitized_signature-9.0.1.0.0.dist-info/DESCRIPTION.rst
odoo9_addon_contract_digitized_signature-9.0.1.0.0.dist-info/METADATA
odoo9_addon_contract_digitized_signature-9.0.1.0.0.dist-info/RECORD
odoo9_addon_contract_digitized_signature-9.0.1.0.0.dist-info/WHEEL
odoo9_addon_contract_digitized_signature-9.0.1.0.0.dist-info/metadata.json
odoo9_addon_contract_digitized_signature-9.0.1.0.0.dist-info/namespace_packages.txt
odoo9_addon_contract_digitized_signature-9.0.1.0.0.dist-info/top_level.txt
odoo_addons/contract_digitized_signature/README.rst
odoo_addons/contract_digitized_signature/__init__.py
odoo_addons/contract_digitized_signature/__openerp__.py
odoo_addons/contract_digitized_signature/i18n/es.po
odoo_addons/contract_digitized_signature/models/__init__.py
odoo_addons/contract_digitized_signature/models/account_analytic_account.py
odoo_addons/contract_digitized_signature/report/report_contract.xml
odoo_addons/contract_digitized_signature/static/description/icon.png
odoo_addons/contract_digitized_signature/tests/__init__.py
odoo_addons/contract_digitized_signature/tests/test_contract_tracking.py
odoo_addons/contract_digitized_signature/views/contract_views.xml
